fectorial/__init__.py
fectorial/fect.py
findfectorial-0.1.dist-info/METADATA
findfectorial-0.1.dist-info/WHEEL
findfectorial-0.1.dist-info/entry_points.txt
findfectorial-0.1.dist-info/top_level.txt
findfectorial-0.1.dist-info/RECORD
