Metadata-Version: 2.1
Name: findfectorial
Version: 0.1
Summary: A package for calculating factorial.
Home-page: https://github.com/Sam-Sisodia/fectorial_calculate.git
Author: Sajal Sisodia
Author-email: sajal89304@gmail.com
Classifier: Programming Language :: Python :: 3
Classifier: License :: OSI Approved :: MIT License
Classifier: Operating System :: OS Independent
